{
  "$schema": "http://schema.management.azure.com/schemas/2015-01-01/deploymentParameters.json#",
  "contentVersion": "1.0.0.0",
  "parameters": {
    "adminUsername": {
      "value": "###########"
    },
    "adminPassword": {
      "value": "###########"
    },
    "dnsNameforLBIP": {
      "value": "###########"
    },
	"storageAccountName": {
	  "value": "############"
	},
	"numberOfInstances": {
	  "value": 2
	},
	"vmNamePrefix": {
	  "value": "WEB"
	},
	"OS": {
	  "value": "Windows"
	},
	"modulesUrl": {
	  "value": "https://github.com/nsucheninov/Azure/raw/master/simple-website/WebServer.ps1.zip"
	},
	"configurationFunction": {
	  "value": "WebServer.ps1\\WebServer"
	},
	"WebSiteName": {
	  "value": "WebSite1"
	}
  }
}
